example_package_bfast3/__init__.py
example_package_bfast3/example.py
example_package_bfast3-0.0.1.dist-info/METADATA
example_package_bfast3-0.0.1.dist-info/WHEEL
example_package_bfast3-0.0.1.dist-info/licenses/LICENSE
example_package_bfast3-0.0.1.dist-info/RECORD
